MANIFEST.in
README.md
setup.cfg
setup.py
tinycert/__init__.py
tinycert/ca.py
tinycert/cert.py
tinycert/session.py
tinycert.egg-info/PKG-INFO
tinycert.egg-info/SOURCES.txt
tinycert.egg-info/dependency_links.txt
tinycert.egg-info/requires.txt
tinycert.egg-info/top_level.txt
tinycert.egg-info/zip-safe