Metadata-Version: 1.1
Name: tinycert
Version: 0.2.0
Summary: TinyCert v1 API wrapper
Home-page: https://github.com/chrisleck/tinycert
Author: Christopher Eck
Author-email: chrisleck@gmail.com
License: MIT
Keywords: tinycert tiny cert x509 pki certificate authority
Platform: any
Classifier: Development Status :: 4 - Beta
Classifier: Intended Audience :: Developers
Classifier: License :: OSI Approved :: MIT License
Classifier: Operating System :: OS Independent
Classifier: Programming Language :: Python
Classifier: Programming Language :: Python :: 2
Classifier: Programming Language :: Python :: 2.7
Classifier: Programming Language :: Python :: 3
Classifier: Programming Language :: Python :: 3.4
Classifier: Topic :: Security
Classifier: Topic :: Security :: Cryptography
Classifier: Topic :: Software Development :: Libraries :: Python Modules
